<root>
<C3_1maze id="0" originalRow="0" groupSign="开始" debugClose="" action="" data="" param="" param2="" param3=""/>
<C3_1maze id="1" originalRow="1" groupSign="" debugClose="" action="" data="" param="" param2="" param3=""/>
<C3_1maze id="2" originalRow="2" groupSign="选择是否离开" debugClose="" action="" data="" param="" param2="" param3=""/>
<C3_1maze id="3" originalRow="3" groupSign="" debugClose="" action="设置镜号" data="avg_basic_story_new" param="no_postprocessing" param2="" param3=""/>
<C3_1maze id="4" originalRow="4" groupSign="" debugClose="" action="角色台词" data="" param="是否离开顶石大厦？" param2="" param3=""/>
<C3_1maze id="5" originalRow="5" groupSign="" debugClose="" action="可选对话框" data="" param="$$离开==&gt;离开
$$先留下来==&gt;结束" param2="" param3=""/>
<C3_1maze id="6" originalRow="6" groupSign="" debugClose="" action="" data="" param="" param2="" param3=""/>
<C3_1maze id="7" originalRow="7" groupSign="" debugClose="" action="" data="" param="" param2="" param3=""/>
<C3_1maze id="8" originalRow="8" groupSign="找到凯瑟琳" debugClose="" action="" data="" param="" param2="" param3=""/>
<C3_1maze id="9" originalRow="9" groupSign="" debugClose="" action="角色台词" data="" param="凯瑟琳！终于见到你了！" param2="" param3=""/>
<C3_1maze id="10" originalRow="10" groupSign="" debugClose="" action="跳转-标签" data="" param="C3_dingshi_outside.户外战斗胜利" param2="" param3=""/>
<C3_1maze id="11" originalRow="11" groupSign="" debugClose="" action="" data="" param="" param2="" param3=""/>
<C3_1maze id="12" originalRow="12" groupSign="开场对话" debugClose="" action="" data="" param="" param2="" param3=""/>
<C3_1maze id="13" originalRow="13" groupSign="" debugClose="" action="角色台词" data="" param="一定要找到凯瑟琳！" param2="" param3=""/>
<C3_1maze id="14" originalRow="14" groupSign="" debugClose="" action="跳转-标签" data="" param="结束" param2="" param3=""/>
<C3_1maze id="15" originalRow="15" groupSign="" debugClose="" action="" data="" param="" param2="" param3=""/>
<C3_1maze id="16" originalRow="16" groupSign="" debugClose="" action="" data="" param="" param2="" param3=""/>
<C3_1maze id="17" originalRow="17" groupSign="" debugClose="" action="" data="" param="" param2="" param3=""/>
<C3_1maze id="18" originalRow="18" groupSign="发现怪物堆" debugClose="" action="" data="" param="" param2="" param3=""/>
<C3_1maze id="19" originalRow="19" groupSign="" debugClose="" action="角色台词" data="" param="前面好多怪物" param2="" param3=""/>
<C3_1maze id="20" originalRow="20" groupSign="" debugClose="" action="角色台词" data="" param="凯瑟琳一定在里面" param2="" param3=""/>
<C3_1maze id="21" originalRow="21" groupSign="" debugClose="" action="跳转-标签" data="" param="结束" param2="" param3=""/>
<C3_1maze id="22" originalRow="22" groupSign="" debugClose="" action="" data="" param="" param2="" param3=""/>
<C3_1maze id="23" originalRow="23" groupSign="" debugClose="" action="" data="" param="" param2="" param3=""/>
<C3_1maze id="24" originalRow="24" groupSign="办公室调查" debugClose="" action="" data="" param="" param2="" param3=""/>
<C3_1maze id="25" originalRow="25" groupSign="" debugClose="" action="角色台词" data="" param="办公室没有凯瑟琳" param2="" param3=""/>
<C3_1maze id="26" originalRow="26" groupSign="" debugClose="" action="跳转-标签" data="" param="结束" param2="" param3=""/>
<C3_1maze id="27" originalRow="27" groupSign="" debugClose="" action="" data="" param="" param2="" param3=""/>
<C3_1maze id="28" originalRow="28" groupSign="" debugClose="" action="" data="" param="" param2="" param3=""/>
<C3_1maze id="29" originalRow="29" groupSign="茶水间调查" debugClose="" action="" data="" param="" param2="" param3=""/>
<C3_1maze id="30" originalRow="30" groupSign="" debugClose="" action="角色台词" data="" param="茶水间没有凯瑟琳" param2="" param3=""/>
<C3_1maze id="31" originalRow="31" groupSign="" debugClose="" action="跳转-标签" data="" param="结束" param2="" param3=""/>
<C3_1maze id="32" originalRow="32" groupSign="" debugClose="" action="" data="" param="" param2="" param3=""/>
<C3_1maze id="33" originalRow="33" groupSign="" debugClose="" action="" data="" param="" param2="" param3=""/>
<C3_1maze id="34" originalRow="34" groupSign="财务室调查" debugClose="" action="" data="" param="" param2="" param3=""/>
<C3_1maze id="35" originalRow="35" groupSign="" debugClose="" action="角色台词" data="" param="财务室没有凯瑟琳" param2="" param3=""/>
<C3_1maze id="36" originalRow="36" groupSign="" debugClose="" action="跳转-标签" data="" param="结束" param2="" param3=""/>
<C3_1maze id="37" originalRow="37" groupSign="" debugClose="" action="" data="" param="" param2="" param3=""/>
<C3_1maze id="38" originalRow="38" groupSign="" debugClose="" action="" data="" param="" param2="" param3=""/>
<C3_1maze id="39" originalRow="39" groupSign="" debugClose="" action="" data="" param="" param2="" param3=""/>
<C3_1maze id="40" originalRow="40" groupSign="打印室调查" debugClose="" action="" data="" param="" param2="" param3=""/>
<C3_1maze id="41" originalRow="41" groupSign="" debugClose="" action="角色台词" data="" param="打印室没有凯瑟琳" param2="" param3=""/>
<C3_1maze id="42" originalRow="42" groupSign="" debugClose="" action="跳转-标签" data="" param="结束" param2="" param3=""/>
<C3_1maze id="43" originalRow="43" groupSign="" debugClose="" action="" data="" param="" param2="" param3=""/>
<C3_1maze id="44" originalRow="44" groupSign="" debugClose="" action="" data="" param="" param2="" param3=""/>
<C3_1maze id="45" originalRow="45" groupSign="" debugClose="" action="" data="" param="" param2="" param3=""/>
<C3_1maze id="46" originalRow="46" groupSign="母婴室调查" debugClose="" action="" data="" param="" param2="" param3=""/>
<C3_1maze id="47" originalRow="47" groupSign="" debugClose="" action="角色台词" data="" param="母婴室没有凯瑟琳" param2="" param3=""/>
<C3_1maze id="48" originalRow="48" groupSign="" debugClose="" action="跳转-标签" data="" param="结束" param2="" param3=""/>
<C3_1maze id="49" originalRow="49" groupSign="" debugClose="" action="" data="" param="" param2="" param3=""/>
<C3_1maze id="50" originalRow="50" groupSign="" debugClose="" action="" data="" param="" param2="" param3=""/>
<C3_1maze id="51" originalRow="51" groupSign="" debugClose="" action="" data="" param="" param2="" param3=""/>
<C3_1maze id="52" originalRow="52" groupSign="" debugClose="" action="" data="" param="" param2="" param3=""/>
<C3_1maze id="53" originalRow="53" groupSign="听到凯瑟琳救援" debugClose="" action="" data="" param="" param2="" param3=""/>
<C3_1maze id="54" originalRow="54" groupSign="" debugClose="" action="角色台词" data="" param="听到了凯瑟琳的声音，继续往前吧" param2="" param3=""/>
<C3_1maze id="55" originalRow="55" groupSign="" debugClose="" action="跳转-标签" data="" param="结束" param2="" param3=""/>
<C3_1maze id="56" originalRow="56" groupSign="" debugClose="" action="" data="" param="" param2="" param3=""/>
<C3_1maze id="57" originalRow="57" groupSign="" debugClose="" action="" data="" param="" param2="" param3=""/>
<C3_1maze id="58" originalRow="58" groupSign="打败门口怪物" debugClose="" action="" data="" param="" param2="" param3=""/>
<C3_1maze id="59" originalRow="59" groupSign="" debugClose="" action="角色台词" data="" param="堵住凯瑟琳的怪物，打败他！" param2="" param3=""/>
<C3_1maze id="60" originalRow="60" groupSign="" debugClose="" action="跳转-标签" data="" param="结束" param2="" param3=""/>
<C3_1maze id="61" originalRow="61" groupSign="" debugClose="" action="" data="" param="" param2="" param3=""/>
<C3_1maze id="62" originalRow="62" groupSign="胜利就在眼前" debugClose="" action="" data="" param="" param2="" param3=""/>
<C3_1maze id="63" originalRow="63" groupSign="" debugClose="" action="角色台词" data="" param="打完这波就能见到凯瑟琳了！" param2="" param3=""/>
<C3_1maze id="64" originalRow="64" groupSign="" debugClose="" action="跳转-标签" data="" param="结束" param2="" param3=""/>
<C3_1maze id="65" originalRow="65" groupSign="" debugClose="" action="" data="" param="" param2="" param3=""/>
<C3_1maze id="66" originalRow="66" groupSign="离开" debugClose="" action="" data="" param="" param2="" param3=""/>
<C3_1maze id="67" originalRow="67" groupSign="" debugClose="" action="切换场景" data="home" param="" param2="" param3=""/>
<C3_1maze id="68" originalRow="68" groupSign="" debugClose="" action="跳转-标签" data="" param="结束" param2="" param3=""/>
<C3_1maze id="69" originalRow="69" groupSign="" debugClose="" action="" data="" param="" param2="" param3=""/>
<C3_1maze id="70" originalRow="70" groupSign="通过avg进入迷宫" debugClose="" action="" data="" param="" param2="" param3=""/>
<C3_1maze id="71" originalRow="71" groupSign="" debugClose="" action="切换场景" data="maze_31" param="" param2="" param3=""/>
<C3_1maze id="72" originalRow="72" groupSign="结束" debugClose="" action="" data="" param="" param2="" param3=""/>
<C3_1maze id="73" originalRow="73" groupSign="" debugClose="" action="" data="" param="" param2="" param3=""/>
<C3_1maze id="74" originalRow="74" groupSign="" debugClose="" action="" data="" param="" param2="" param3=""/>
</root>