<root>
<hezhongshaonv000_duheng id="0" originalRow="0" groupSign="开始"/>
<hezhongshaonv000_duheng id="1" originalRow="1" groupSign="" action="角色台词" data="duheng" param="@周易 周易，收到回答。"/>
<hezhongshaonv000_duheng id="2" originalRow="2" action="可选对话框" data="" param="$$不回复==&gt;任务发布2
$$在！老板请指示！==&gt;任务发布1"/>
<hezhongshaonv000_duheng id="3" originalRow="3" groupSign="任务发布1" action="角色台词" data="wo" param="在！老板请指示！"/>
<hezhongshaonv000_duheng id="4" originalRow="4" groupSign="1&gt;&gt;" action="角色台词" data="duheng" param="测试一下你有没有摸鱼，果然在认真工作呢。"/>
<hezhongshaonv000_duheng id="5" originalRow="5" action="角色台词" data="wo" param="嗐，不要做这种无聊的测试啊喂。"/>
<hezhongshaonv000_duheng id="6" originalRow="6" groupSign="2&gt;&gt;" action="角色台词" data="duheng" param="嘛，也不是完全没事。我收到了一份异质物目击报告，据说是专门袭击独居青年的“盒中少女”。"/>
<hezhongshaonv000_duheng id="7" originalRow="7" action="语法-数值" data="QUEST_盒中的神秘少女=1"/>
<hezhongshaonv000_duheng id="8" originalRow="8" groupSign="1&gt;&gt;" action="角色台词" data="duheng" param="报告者是住在安太公寓，和@周易 一样的社畜独居男青年。"/>
<hezhongshaonv000_duheng id="9" originalRow="9" groupSign="1&gt;&gt;" action="角色台词" data="duheng" param="报告里也说的很模糊，总之你们现在就去看看吧。"/>
<hezhongshaonv000_duheng id="10" originalRow="10" action="可选对话框" data="" param="$$不回复==&gt;结束
$$好的！我现在就去！==&gt;结束1"/>
<hezhongshaonv000_duheng id="11" originalRow="11"/>
<hezhongshaonv000_duheng id="12" originalRow="12" groupSign="结束1" action="角色台词" data="wo" param="好的！我现在就去！"/>
<hezhongshaonv000_duheng id="13" originalRow="13" action="跳转-标签" data="" param="结束"/>
<hezhongshaonv000_duheng id="14" originalRow="14" action="" data="" param=""/>
<hezhongshaonv000_duheng id="15" originalRow="15" groupSign="任务发布2" action="角色台词" data="duheng" param="我收到了一份异质物目击报告，据说是专门袭击独居青年的“盒中少女”。"/>
<hezhongshaonv000_duheng id="16" originalRow="16" action="语法-数值" data="QUEST_盒中的神秘少女=1" param=""/>
<hezhongshaonv000_duheng id="17" originalRow="17" groupSign="1&gt;&gt;" action="角色台词" data="duheng" param="报告者是住在安太公寓，和@周易 一样的社畜独居男青年。报告里也说的很模糊。"/>
<hezhongshaonv000_duheng id="18" originalRow="18" groupSign="1&gt;&gt;" action="角色台词" data="duheng" param="任务已经发到你那里去了，你们现在就去看看吧。"/>
<hezhongshaonv000_duheng id="19" originalRow="19" action="可选对话框" data="" param="$$不回复==&gt;结束
$$好的！我现在就去！==&gt;结束1"/>
<hezhongshaonv000_duheng id="20" originalRow="20" groupSign="结束"/>
</root>