<root>
<xt_xiangji_start id="0" originalRow="0" groupSign="开始" debugClose="" action="" data="" param="" param2="" param3=""/>
<xt_xiangji_start id="1" originalRow="1" groupSign="" debugClose="" action="设置镜号" data="avg_basic_story_new" param="" param2="" param3=""/>
<xt_xiangji_start id="2" originalRow="2" groupSign="" debugClose="" action="设置角色" data="niefei" param="pos=中" param2="聂总_紧张_动作_开始_01" param3=""/>
<xt_xiangji_start id="3" originalRow="3" groupSign="" debugClose="" action="角色台词" data="wo" param="聂总！你在这里干嘛？" param2="" param3="type=0"/>
<xt_xiangji_start id="4" originalRow="4" groupSign="" debugClose="" action="角色台词" data="kaiselin02" param="欸？是周易吗？哎呀呀，没想到你刚好也在呢。" param2="" param3="type=4"/>
<xt_xiangji_start id="5" originalRow="5" groupSign="" debugClose="" action="角色台词" data="kaiselin02" param="让我来说明情况吧。
昭离公馆接到报案，报案人是一个摄影店的老板。" param2="" param3="type=4"/>
<xt_xiangji_start id="6" originalRow="6" groupSign="" debugClose="" action="打开插画" data="xt_3006_568photo" param="" param2="" param3=""/>
<xt_xiangji_start id="7" originalRow="7" groupSign="" debugClose="" action="" data="" param="" param2="" param3=""/>
<xt_xiangji_start id="8" originalRow="8" groupSign="" debugClose="" action="角色台词" data="kaiselin02" param="据他所说，一周前突然出现了一个手持拍立得的陌生少女，一直在附近徘徊，免费给人拍照。" param2="" param3="type=4"/>
<xt_xiangji_start id="9" originalRow="9" groupSign="" debugClose="" action="角色台词" data="niefei" param="这有什么奇怪的？" param2="" param3="type=0"/>
<xt_xiangji_start id="10" originalRow="10" groupSign="" debugClose="" action="角色台词" data="kaiselin02" param="{shake=1}别打断我啊蠢猫！…咳咳，失态了。周易，虽然你是路过，但你想现在处理这个事件吗？" param2="" param3="type=4"/>
<xt_xiangji_start id="11" originalRow="11" groupSign="" debugClose="" action="可选对话框" data="" param="$$现在处理==&gt;现在处理
$$延后处理==&gt;延后处理" param2="" param3=""/>
<xt_xiangji_start id="12" originalRow="12" groupSign="" debugClose="" action="" data="" param="" param2="" param3=""/>
<xt_xiangji_start id="13" originalRow="13" groupSign="延后处理" debugClose="" action="" data="" param="" param2="" param3=""/>
<xt_xiangji_start id="14" originalRow="14" groupSign="" debugClose="" action="角色台词" data="wo" param="我还有其他的事要忙，这件事先放一下吧。" param2="" param3="type=0"/>
<xt_xiangji_start id="15" originalRow="15" groupSign="" debugClose="" action="关闭插画" data="" param="" param2="" param3=""/>
<xt_xiangji_start id="16" originalRow="16" groupSign="" debugClose="" action="结束且返回值" data="" param="FALSE" param2="" param3=""/>
<xt_xiangji_start id="17" originalRow="17" groupSign="" debugClose="" action="" data="" param="" param2="" param3=""/>
<xt_xiangji_start id="18" originalRow="18" groupSign="" debugClose="" action="" data="" param="" param2="" param3=""/>
<xt_xiangji_start id="19" originalRow="19" groupSign="现在处理" debugClose="" action="" data="" param="" param2="" param3=""/>
<xt_xiangji_start id="20" originalRow="20" groupSign="" debugClose="" action="角色台词" data="wo" param="择日不如撞日，
既然接到报案了，还是早点处理委托比较好吧。" param2="" param3=""/>
<xt_xiangji_start id="21" originalRow="21" groupSign="" debugClose="" action="角色台词" data="kaiselin02" param="很好，老板说那些人被拍完照后精神状态都出现了问题，只能送去精神科治疗。怀疑和异质物有关。" param2="" param3="type=4"/>
<xt_xiangji_start id="22" originalRow="22" groupSign="" debugClose="" action="角色台词" data="kaiselin02" param="更多信息等我和涂凌赶到现场协助你们，我们一起行动。" param2="" param3="type=4"/>
<xt_xiangji_start id="23" originalRow="23" groupSign="" debugClose="" action="角色台词" data="tuling" param="你们就呆在原地不要走动！" param2="" param3="type=4"/>
<xt_xiangji_start id="24" originalRow="24" groupSign="" debugClose="" action="关闭插画" data="" param="" param2="" param3=""/>
<xt_xiangji_start id="25" originalRow="25" groupSign="" debugClose="" action="移除角色" data="" param="" param2="" param3=""/>
<xt_xiangji_start id="26" originalRow="26" groupSign="1&gt;&gt;" debugClose="" action="故事板" data="" param="不久以后，涂凌和凯瑟琳也到了……" param2="" param3=""/>
<xt_xiangji_start id="27" originalRow="27" groupSign="" debugClose="" action="" data="" param="" param2="" param3=""/>
<xt_xiangji_start id="28" originalRow="28" groupSign="" debugClose="" action="跳转-标签" data="" param="结束" param2="" param3=""/>
<xt_xiangji_start id="29" originalRow="29" groupSign="" debugClose="" action="" data="" param="" param2="" param3=""/>
<xt_xiangji_start id="30" originalRow="30" groupSign="" debugClose="" action="" data="" param="" param2="" param3=""/>
<xt_xiangji_start id="31" originalRow="31" groupSign="聂飞问候" debugClose="" action="" data="" param="" param2="" param3=""/>
<xt_xiangji_start id="32" originalRow="32" groupSign="" debugClose="" action="设置镜号" data="avg_basic_story_new" param="" param2="" param3=""/>
<xt_xiangji_start id="33" originalRow="33" groupSign="" debugClose="" action="设置角色" data="niefei" param="pos=中" param2="" param3=""/>
<xt_xiangji_start id="34" originalRow="34" groupSign="" debugClose="" action="角色台词" data="niefei" param="叫本大爷干嘛？" param2="" param3=""/>
<xt_xiangji_start id="35" originalRow="35" groupSign="" debugClose="" action="跳转-标签" data="" param="结束" param2="" param3=""/>
<xt_xiangji_start id="36" originalRow="36" groupSign="" debugClose="" action="" data="" param="" param2="" param3=""/>
<xt_xiangji_start id="37" originalRow="37" groupSign="结束" debugClose="" action="" data="" param="" param2="" param3=""/>
<xt_xiangji_start id="38" originalRow="38" groupSign="" debugClose="" action="" data="" param="" param2="" param3=""/>
</root>